LICENSE
MANIFEST.in
README.md
setup.cfg
setup.py
clone_github/__init__.py
clone_github/clone_github.py
clone_github.egg-info/PKG-INFO
clone_github.egg-info/SOURCES.txt
clone_github.egg-info/dependency_links.txt
clone_github.egg-info/entry_points.txt
clone_github.egg-info/top_level.txt